examples/__init__.py
examples/main.py
xflow/__init__.py
xflow/seed.py
xflow/util.py
xflow/visualization.py
xflow/dataset/__init__.py
xflow/dataset/nx.py
xflow/dataset/pyg.py
xflow/diffusion/IC.py
xflow/diffusion/LT.py
xflow/diffusion/SI.py
xflow/diffusion/__init__.py
xflow/method/__init__.py
xflow/method/ibm.py
xflow/method/im.py
xflow/method/sl.py
xflow/method/cosasi/__init__.py
xflow/method/cosasi/benchmark/__init__.py
xflow/method/cosasi/benchmark/benchmark.py
xflow/method/cosasi/contagion/__init__.py
xflow/method/cosasi/contagion/static_network_contagion.py
xflow/method/cosasi/source_inference/__init__.py
xflow/method/cosasi/source_inference/algorithm_details.json
xflow/method/cosasi/source_inference/source_results.py
xflow/method/cosasi/source_inference/multiple_source/__init__.py
xflow/method/cosasi/source_inference/multiple_source/jordan.py
xflow/method/cosasi/source_inference/multiple_source/lisn.py
xflow/method/cosasi/source_inference/multiple_source/netsleuth.py
xflow/method/cosasi/source_inference/single_source/__init__.py
xflow/method/cosasi/source_inference/single_source/earliest_infection_first.py
xflow/method/cosasi/source_inference/single_source/jordan.py
xflow/method/cosasi/source_inference/single_source/lisn.py
xflow/method/cosasi/source_inference/single_source/netsleuth.py
xflow/method/cosasi/source_inference/single_source/rumor_centrality.py
xflow/method/cosasi/source_inference/single_source/short_fat_tree.py
xflow/method/cosasi/utils/__init__.py
xflow/method/cosasi/utils/estimators.py
xflow/method/cosasi/utils/helpers.py
xflow_net-0.1.3.dist-info/LICENSE
xflow_net-0.1.3.dist-info/METADATA
xflow_net-0.1.3.dist-info/WHEEL
xflow_net-0.1.3.dist-info/top_level.txt
xflow_net-0.1.3.dist-info/RECORD
