Metadata-Version: 2.1
Name: xflow-net
Version: 0.1.3
Summary: a python library for graph flow
Home-page: https://xflow.network/
Author: XGraphing
Author-email: zchen@cse.msstate.edu
License: MIT
Classifier: License :: OSI Approved :: MIT License
Classifier: Programming Language :: Python :: 3
Classifier: Programming Language :: Python :: Implementation :: CPython
Classifier: Programming Language :: Python :: Implementation :: PyPy
Classifier: Operating System :: OS Independent
Requires-Python: >=3.6.0
License-File: LICENSE
Requires-Dist: networkx
Requires-Dist: ndlib
Requires-Dist: torch-geometric
Requires-Dist: cosasi
